{"current": [{"timestamp": "2025-02-25T11:51:01.775576", "cpu_usage": 0.4, "cpu_usage_per_core": [0.0, 0.0, 0.0, 0.0, 0.0, 0.0, 4.0, 0.0, 0.0, 1.0, 0.0, 0.0], "memory_usage": 5.9, "disk_usage": 3.6, "cpu_temp": 43.5, "gpu_temp": 43.0, "gpu_usage": [{"index": 0, "name": "NVIDIA GeForce GTX 1650 Ti", "usage": 0}], "nvme_temp": 33.9, "uptime": 1740172247.0}, {"timestamp": "2025-02-25T11:51:05.050257", "cpu_usage": 0.3, "cpu_usage_per_core": [0.0, 0.0, 1.0, 0.0, 0.0, 0.0, 1.0, 0.0, 0.0, 1.0, 0.0, 0.0], "memory_usage": 5.8, "disk_usage": 3.6, "cpu_temp": 43.5, "gpu_temp": 43.0, "gpu_usage": [{"index": 0, "name": "NVIDIA GeForce GTX 1650 Ti", "usage": 0}], "nvme_temp": 33.9, "uptime": 1740172247.0}, {"timestamp": "2025-02-25T11:51:08.354858", "cpu_usage": 0.3, "cpu_usage_per_core": [0.0, 0.0, 0.0, 0.0, 0.0, 0.0, 0.0, 0.0, 0.0, 1.0, 0.0, 1.0], "memory_usage": 5.8, "disk_usage": 3.6, "cpu_temp": 43.5, "gpu_temp": 43.0, "gpu_usage": [{"index": 0, "name": "NVIDIA GeForce GTX 1650 Ti", "usage": 0}], "nvme_temp": 32.9, "uptime": 1740172247.0}, {"timestamp": "2025-02-25T11:51:11.725856", "cpu_usage": 0.3, "cpu_usage_per_core": [1.0, 0.0, 0.0, 0.0, 0.0, 0.0, 1.0, 0.0, 0.0, 1.0, 0.0, 1.0], "memory_usage": 5.8, "disk_usage": 3.6, "cpu_temp": 43.5, "gpu_temp": 43.0, "gpu_usage": [{"index": 0, "name": "NVIDIA GeForce GTX 1650 Ti", "usage": 0}], "nvme_temp": 32.9, "uptime": 1740172247.0}, {"timestamp": "2025-02-25T11:51:15.066255", "cpu_usage": 0.4, "cpu_usage_per_core": [0.0, 0.0, 0.0, 0.0, 1.0, 0.0, 1.0, 0.0, 0.0, 1.0, 1.0, 0.0], "memory_usage": 5.8, "disk_usage": 3.6, "cpu_temp": 43.5, "gpu_temp": 43.0, "gpu_usage": [{"index": 0, "name": "NVIDIA GeForce GTX 1650 Ti", "usage": 0}], "nvme_temp": 32.9, "uptime": 1740172247.0}, {"timestamp": "2025-02-25T11:51:18.419466", "cpu_usage": 0.2, "cpu_usage_per_core": [1.0, 0.0, 0.0, 0.0, 0.0, 0.0, 0.0, 0.0, 0.0, 1.0, 2.0, 0.0], "memory_usage": 5.8, "disk_usage": 3.6, "cpu_temp": 43.5, "gpu_temp": 43.0, "gpu_usage": [{"index": 0, "name": "NVIDIA GeForce GTX 1650 Ti", "usage": 0}], "nvme_temp": 32.9, "uptime": 1740172247.0}, {"timestamp": "2025-02-25T11:51:21.759508", "cpu_usage": 0.3, "cpu_usage_per_core": [1.0, 0.0, 0.0, 0.0, 0.0, 0.0, 1.0, 0.0, 0.0, 0.0, 1.0, 0.0], "memory_usage": 5.8, "disk_usage": 3.6, "cpu_temp": 43.5, "gpu_temp": 43.0, "gpu_usage": [{"index": 0, "name": "NVIDIA GeForce GTX 1650 Ti", "usage": 0}], "nvme_temp": 32.9, "uptime": 1740172247.0}, {"timestamp": "2025-02-25T11:51:25.086879", "cpu_usage": 0.3, "cpu_usage_per_core": [0.0, 0.0, 0.0, 0.0, 0.0, 0.0, 0.0, 0.0, 1.0, 0.0, 1.0, 0.0], "memory_usage": 5.8, "disk_usage": 3.6, "cpu_temp": 43.5, "gpu_temp": 43.0, "gpu_usage": [{"index": 0, "name": "NVIDIA GeForce GTX 1650 Ti", "usage": 0}], "nvme_temp": 32.9, "uptime": 1740172247.0}, {"timestamp": "2025-02-25T11:51:28.427816", "cpu_usage": 0.3, "cpu_usage_per_core": [0.0, 0.0, 0.0, 0.0, 0.0, 0.0, 2.0, 0.0, 0.0, 0.0, 0.0, 0.0], "memory_usage": 5.8, "disk_usage": 3.6, "cpu_temp": 43.6, "gpu_temp": 43.0, "gpu_usage": [{"index": 0, "name": "NVIDIA GeForce GTX 1650 Ti", "usage": 0}], "nvme_temp": 32.9, "uptime": 1740172247.0}, {"timestamp": "2025-02-25T11:51:31.709037", "cpu_usage": 0.3, "cpu_usage_per_core": [0.0, 0.0, 0.0, 0.0, 0.0, 0.0, 2.0, 0.0, 0.0, 2.0, 0.0, 0.0], "memory_usage": 5.8, "disk_usage": 3.6, "cpu_temp": 43.6, "gpu_temp": 43.0, "gpu_usage": [{"index": 0, "name": "NVIDIA GeForce GTX 1650 Ti", "usage": 0}], "nvme_temp": 32.9, "uptime": 1740172247.0}, {"timestamp": "2025-02-25T11:51:35.000999", "cpu_usage": 0.3, "cpu_usage_per_core": [0.0, 0.0, 0.0, 0.0, 0.0, 0.0, 1.0, 0.0, 0.0, 1.0, 0.0, 1.0], "memory_usage": 5.8, "disk_usage": 3.6, "cpu_temp": 43.6, "gpu_temp": 43.0, "gpu_usage": [{"index": 0, "name": "NVIDIA GeForce GTX 1650 Ti", "usage": 0}], "nvme_temp": 32.9, "uptime": 1740172247.0}, {"timestamp": "2025-02-25T11:51:38.306542", "cpu_usage": 0.2, "cpu_usage_per_core": [0.0, 0.0, 0.0, 0.0, 0.0, 1.0, 1.0, 0.0, 0.0, 1.0, 1.0, 0.0], "memory_usage": 5.8, "disk_usage": 3.6, "cpu_temp": 43.6, "gpu_temp": 43.0, "gpu_usage": [{"index": 0, "name": "NVIDIA GeForce GTX 1650 Ti", "usage": 0}], "nvme_temp": 31.9, "uptime": 1740172247.0}, {"timestamp": "2025-02-25T11:51:41.584558", "cpu_usage": 0.2, "cpu_usage_per_core": [0.0, 0.0, 0.0, 0.0, 0.0, 0.0, 0.0, 0.0, 0.0, 1.0, 2.0, 0.0], "memory_usage": 5.8, "disk_usage": 3.6, "cpu_temp": 43.6, "gpu_temp": 43.0, "gpu_usage": [{"index": 0, "name": "NVIDIA GeForce GTX 1650 Ti", "usage": 0}], "nvme_temp": 31.9, "uptime": 1740172247.0}, {"timestamp": "2025-02-25T11:51:44.910680", "cpu_usage": 0.3, "cpu_usage_per_core": [1.0, 0.0, 1.0, 0.0, 0.0, 0.0, 1.0, 0.0, 0.0, 1.0, 1.0, 0.0], "memory_usage": 5.8, "disk_usage": 3.6, "cpu_temp": 43.8, "gpu_temp": 43.0, "gpu_usage": [{"index": 0, "name": "NVIDIA GeForce GTX 1650 Ti", "usage": 0}], "nvme_temp": 32.9, "uptime": 1740172247.0}, {"timestamp": "2025-02-25T11:51:48.246071", "cpu_usage": 0.2, "cpu_usage_per_core": [0.0, 0.0, 0.0, 0.0, 0.0, 0.0, 1.0, 0.0, 1.0, 0.0, 0.0, 0.0], "memory_usage": 5.8, "disk_usage": 3.6, "cpu_temp": 43.8, "gpu_temp": 43.0, "gpu_usage": [{"index": 0, "name": "NVIDIA GeForce GTX 1650 Ti", "usage": 0}], "nvme_temp": 32.9, "uptime": 1740172247.0}, {"timestamp": "2025-02-25T11:51:51.500002", "cpu_usage": 0.2, "cpu_usage_per_core": [0.0, 0.0, 0.0, 0.0, 0.0, 1.0, 1.0, 0.0, 0.0, 1.0, 1.0, 0.0], "memory_usage": 5.8, "disk_usage": 3.6, "cpu_temp": 43.8, "gpu_temp": 43.0, "gpu_usage": [{"index": 0, "name": "NVIDIA GeForce GTX 1650 Ti", "usage": 0}], "nvme_temp": 32.9, "uptime": 1740172247.0}, {"timestamp": "2025-02-25T11:51:54.771613", "cpu_usage": 0.4, "cpu_usage_per_core": [0.0, 0.0, 0.0, 0.0, 0.0, 0.0, 0.0, 0.0, 0.0, 1.0, 1.0, 0.0], "memory_usage": 5.8, "disk_usage": 3.6, "cpu_temp": 43.8, "gpu_temp": 44.0, "gpu_usage": [{"index": 0, "name": "NVIDIA GeForce GTX 1650 Ti", "usage": 0}], "nvme_temp": 32.9, "uptime": 1740172247.0}, {"timestamp": "2025-02-25T11:51:58.042345", "cpu_usage": 0.2, "cpu_usage_per_core": [0.0, 1.0, 0.0, 0.0, 1.0, 1.0, 0.0, 0.0, 0.0, 1.0, 2.0, 0.0], "memory_usage": 5.8, "disk_usage": 3.6, "cpu_temp": 43.8, "gpu_temp": 43.0, "gpu_usage": [{"index": 0, "name": "NVIDIA GeForce GTX 1650 Ti", "usage": 0}], "nvme_temp": 32.9, "uptime": 1740172247.0}, {"timestamp": "2025-02-25T11:52:01.330970", "cpu_usage": 0.9, "cpu_usage_per_core": [0.0, 0.0, 0.0, 0.0, 0.0, 1.0, 0.0, 0.0, 0.0, 1.0, 0.0, 0.0], "memory_usage": 5.8, "disk_usage": 3.6, "cpu_temp": 43.8, "gpu_temp": 43.0, "gpu_usage": [{"index": 0, "name": "NVIDIA GeForce GTX 1650 Ti", "usage": 0}], "nvme_temp": 32.9, "uptime": 1740172247.0}], "historical": [[{"timestamp": "2025-02-25T11:51:01.775576", "cpu_usage": 0.4, "cpu_usage_per_core": [0.0, 0.0, 0.0, 0.0, 0.0, 0.0, 4.0, 0.0, 0.0, 1.0, 0.0, 0.0], "memory_usage": 5.9, "disk_usage": 3.6, "cpu_temp": 43.5, "gpu_temp": 43.0, "gpu_usage": [{"index": 0, "name": "NVIDIA GeForce GTX 1650 Ti", "usage": 0}], "nvme_temp": 33.9, "uptime": 1740172247.0}, {"timestamp": "2025-02-25T11:51:05.050257", "cpu_usage": 0.3, "cpu_usage_per_core": [0.0, 0.0, 1.0, 0.0, 0.0, 0.0, 1.0, 0.0, 0.0, 1.0, 0.0, 0.0], "memory_usage": 5.8, "disk_usage": 3.6, "cpu_temp": 43.5, "gpu_temp": 43.0, "gpu_usage": [{"index": 0, "name": "NVIDIA GeForce GTX 1650 Ti", "usage": 0}], "nvme_temp": 33.9, "uptime": 1740172247.0}, {"timestamp": "2025-02-25T11:51:08.354858", "cpu_usage": 0.3, "cpu_usage_per_core": [0.0, 0.0, 0.0, 0.0, 0.0, 0.0, 0.0, 0.0, 0.0, 1.0, 0.0, 1.0], "memory_usage": 5.8, "disk_usage": 3.6, "cpu_temp": 43.5, "gpu_temp": 43.0, "gpu_usage": [{"index": 0, "name": "NVIDIA GeForce GTX 1650 Ti", "usage": 0}], "nvme_temp": 32.9, "uptime": 1740172247.0}, {"timestamp": "2025-02-25T11:51:11.725856", "cpu_usage": 0.3, "cpu_usage_per_core": [1.0, 0.0, 0.0, 0.0, 0.0, 0.0, 1.0, 0.0, 0.0, 1.0, 0.0, 1.0], "memory_usage": 5.8, "disk_usage": 3.6, "cpu_temp": 43.5, "gpu_temp": 43.0, "gpu_usage": [{"index": 0, "name": "NVIDIA GeForce GTX 1650 Ti", "usage": 0}], "nvme_temp": 32.9, "uptime": 1740172247.0}, {"timestamp": "2025-02-25T11:51:15.066255", "cpu_usage": 0.4, "cpu_usage_per_core": [0.0, 0.0, 0.0, 0.0, 1.0, 0.0, 1.0, 0.0, 0.0, 1.0, 1.0, 0.0], "memory_usage": 5.8, "disk_usage": 3.6, "cpu_temp": 43.5, "gpu_temp": 43.0, "gpu_usage": [{"index": 0, "name": "NVIDIA GeForce GTX 1650 Ti", "usage": 0}], "nvme_temp": 32.9, "uptime": 1740172247.0}, {"timestamp": "2025-02-25T11:51:18.419466", "cpu_usage": 0.2, "cpu_usage_per_core": [1.0, 0.0, 0.0, 0.0, 0.0, 0.0, 0.0, 0.0, 0.0, 1.0, 2.0, 0.0], "memory_usage": 5.8, "disk_usage": 3.6, "cpu_temp": 43.5, "gpu_temp": 43.0, "gpu_usage": [{"index": 0, "name": "NVIDIA GeForce GTX 1650 Ti", "usage": 0}], "nvme_temp": 32.9, "uptime": 1740172247.0}, {"timestamp": "2025-02-25T11:51:21.759508", "cpu_usage": 0.3, "cpu_usage_per_core": [1.0, 0.0, 0.0, 0.0, 0.0, 0.0, 1.0, 0.0, 0.0, 0.0, 1.0, 0.0], "memory_usage": 5.8, "disk_usage": 3.6, "cpu_temp": 43.5, "gpu_temp": 43.0, "gpu_usage": [{"index": 0, "name": "NVIDIA GeForce GTX 1650 Ti", "usage": 0}], "nvme_temp": 32.9, "uptime": 1740172247.0}, {"timestamp": "2025-02-25T11:51:25.086879", "cpu_usage": 0.3, "cpu_usage_per_core": [0.0, 0.0, 0.0, 0.0, 0.0, 0.0, 0.0, 0.0, 1.0, 0.0, 1.0, 0.0], "memory_usage": 5.8, "disk_usage": 3.6, "cpu_temp": 43.5, "gpu_temp": 43.0, "gpu_usage": [{"index": 0, "name": "NVIDIA GeForce GTX 1650 Ti", "usage": 0}], "nvme_temp": 32.9, "uptime": 1740172247.0}, {"timestamp": "2025-02-25T11:51:28.427816", "cpu_usage": 0.3, "cpu_usage_per_core": [0.0, 0.0, 0.0, 0.0, 0.0, 0.0, 2.0, 0.0, 0.0, 0.0, 0.0, 0.0], "memory_usage": 5.8, "disk_usage": 3.6, "cpu_temp": 43.6, "gpu_temp": 43.0, "gpu_usage": [{"index": 0, "name": "NVIDIA GeForce GTX 1650 Ti", "usage": 0}], "nvme_temp": 32.9, "uptime": 1740172247.0}, {"timestamp": "2025-02-25T11:51:31.709037", "cpu_usage": 0.3, "cpu_usage_per_core": [0.0, 0.0, 0.0, 0.0, 0.0, 0.0, 2.0, 0.0, 0.0, 2.0, 0.0, 0.0], "memory_usage": 5.8, "disk_usage": 3.6, "cpu_temp": 43.6, "gpu_temp": 43.0, "gpu_usage": [{"index": 0, "name": "NVIDIA GeForce GTX 1650 Ti", "usage": 0}], "nvme_temp": 32.9, "uptime": 1740172247.0}, {"timestamp": "2025-02-25T11:51:35.000999", "cpu_usage": 0.3, "cpu_usage_per_core": [0.0, 0.0, 0.0, 0.0, 0.0, 0.0, 1.0, 0.0, 0.0, 1.0, 0.0, 1.0], "memory_usage": 5.8, "disk_usage": 3.6, "cpu_temp": 43.6, "gpu_temp": 43.0, "gpu_usage": [{"index": 0, "name": "NVIDIA GeForce GTX 1650 Ti", "usage": 0}], "nvme_temp": 32.9, "uptime": 1740172247.0}, {"timestamp": "2025-02-25T11:51:38.306542", "cpu_usage": 0.2, "cpu_usage_per_core": [0.0, 0.0, 0.0, 0.0, 0.0, 1.0, 1.0, 0.0, 0.0, 1.0, 1.0, 0.0], "memory_usage": 5.8, "disk_usage": 3.6, "cpu_temp": 43.6, "gpu_temp": 43.0, "gpu_usage": [{"index": 0, "name": "NVIDIA GeForce GTX 1650 Ti", "usage": 0}], "nvme_temp": 31.9, "uptime": 1740172247.0}, {"timestamp": "2025-02-25T11:51:41.584558", "cpu_usage": 0.2, "cpu_usage_per_core": [0.0, 0.0, 0.0, 0.0, 0.0, 0.0, 0.0, 0.0, 0.0, 1.0, 2.0, 0.0], "memory_usage": 5.8, "disk_usage": 3.6, "cpu_temp": 43.6, "gpu_temp": 43.0, "gpu_usage": [{"index": 0, "name": "NVIDIA GeForce GTX 1650 Ti", "usage": 0}], "nvme_temp": 31.9, "uptime": 1740172247.0}, {"timestamp": "2025-02-25T11:51:44.910680", "cpu_usage": 0.3, "cpu_usage_per_core": [1.0, 0.0, 1.0, 0.0, 0.0, 0.0, 1.0, 0.0, 0.0, 1.0, 1.0, 0.0], "memory_usage": 5.8, "disk_usage": 3.6, "cpu_temp": 43.8, "gpu_temp": 43.0, "gpu_usage": [{"index": 0, "name": "NVIDIA GeForce GTX 1650 Ti", "usage": 0}], "nvme_temp": 32.9, "uptime": 1740172247.0}, {"timestamp": "2025-02-25T11:51:48.246071", "cpu_usage": 0.2, "cpu_usage_per_core": [0.0, 0.0, 0.0, 0.0, 0.0, 0.0, 1.0, 0.0, 1.0, 0.0, 0.0, 0.0], "memory_usage": 5.8, "disk_usage": 3.6, "cpu_temp": 43.8, "gpu_temp": 43.0, "gpu_usage": [{"index": 0, "name": "NVIDIA GeForce GTX 1650 Ti", "usage": 0}], "nvme_temp": 32.9, "uptime": 1740172247.0}, {"timestamp": "2025-02-25T11:51:51.500002", "cpu_usage": 0.2, "cpu_usage_per_core": [0.0, 0.0, 0.0, 0.0, 0.0, 1.0, 1.0, 0.0, 0.0, 1.0, 1.0, 0.0], "memory_usage": 5.8, "disk_usage": 3.6, "cpu_temp": 43.8, "gpu_temp": 43.0, "gpu_usage": [{"index": 0, "name": "NVIDIA GeForce GTX 1650 Ti", "usage": 0}], "nvme_temp": 32.9, "uptime": 1740172247.0}, {"timestamp": "2025-02-25T11:51:54.771613", "cpu_usage": 0.4, "cpu_usage_per_core": [0.0, 0.0, 0.0, 0.0, 0.0, 0.0, 0.0, 0.0, 0.0, 1.0, 1.0, 0.0], "memory_usage": 5.8, "disk_usage": 3.6, "cpu_temp": 43.8, "gpu_temp": 44.0, "gpu_usage": [{"index": 0, "name": "NVIDIA GeForce GTX 1650 Ti", "usage": 0}], "nvme_temp": 32.9, "uptime": 1740172247.0}, {"timestamp": "2025-02-25T11:51:58.042345", "cpu_usage": 0.2, "cpu_usage_per_core": [0.0, 1.0, 0.0, 0.0, 1.0, 1.0, 0.0, 0.0, 0.0, 1.0, 2.0, 0.0], "memory_usage": 5.8, "disk_usage": 3.6, "cpu_temp": 43.8, "gpu_temp": 43.0, "gpu_usage": [{"index": 0, "name": "NVIDIA GeForce GTX 1650 Ti", "usage": 0}], "nvme_temp": 32.9, "uptime": 1740172247.0}, {"timestamp": "2025-02-25T11:52:01.330970", "cpu_usage": 0.9, "cpu_usage_per_core": [0.0, 0.0, 0.0, 0.0, 0.0, 1.0, 0.0, 0.0, 0.0, 1.0, 0.0, 0.0], "memory_usage": 5.8, "disk_usage": 3.6, "cpu_temp": 43.8, "gpu_temp": 43.0, "gpu_usage": [{"index": 0, "name": "NVIDIA GeForce GTX 1650 Ti", "usage": 0}], "nvme_temp": 32.9, "uptime": 1740172247.0}]]}