{"current": [{"timestamp": "2025-02-25T12:48:01.644276", "cpu_usage": 0.3, "cpu_usage_per_core": [1.0, 0.0, 0.0, 1.0, 1.0, 0.0, 1.0, 0.0, 0.0, 1.0, 4.9, 0.0], "memory_usage": 5.9, "disk_usage": 3.6, "cpu_temp": 41.2, "gpu_temp": 40.0, "gpu_usage": [{"index": 0, "name": "NVIDIA GeForce GTX 1650 Ti", "usage": 0}], "nvme_temp": 34.9, "uptime": 1740172247.0}, {"timestamp": "2025-02-25T12:48:04.898207", "cpu_usage": 0.3, "cpu_usage_per_core": [0.0, 0.0, 0.0, 0.0, 1.0, 0.0, 1.0, 0.0, 1.0, 0.0, 0.0, 0.0], "memory_usage": 5.8, "disk_usage": 3.6, "cpu_temp": 41.2, "gpu_temp": 40.0, "gpu_usage": [{"index": 0, "name": "NVIDIA GeForce GTX 1650 Ti", "usage": 0}], "nvme_temp": 31.9, "uptime": 1740172247.0}, {"timestamp": "2025-02-25T12:48:08.174531", "cpu_usage": 0.3, "cpu_usage_per_core": [1.0, 0.0, 0.0, 0.0, 0.0, 0.0, 0.0, 0.0, 0.0, 1.0, 2.0, 0.0], "memory_usage": 5.8, "disk_usage": 3.6, "cpu_temp": 41.2, "gpu_temp": 39.0, "gpu_usage": [{"index": 0, "name": "NVIDIA GeForce GTX 1650 Ti", "usage": 0}], "nvme_temp": 30.9, "uptime": 1740172247.0}, {"timestamp": "2025-02-25T12:48:11.468512", "cpu_usage": 0.3, "cpu_usage_per_core": [2.0, 0.0, 0.0, 0.0, 0.0, 0.0, 0.0, 0.0, 0.0, 0.0, 0.0, 0.0], "memory_usage": 5.9, "disk_usage": 3.6, "cpu_temp": 41.2, "gpu_temp": 40.0, "gpu_usage": [{"index": 0, "name": "NVIDIA GeForce GTX 1650 Ti", "usage": 0}], "nvme_temp": 30.9, "uptime": 1740172247.0}, {"timestamp": "2025-02-25T12:48:14.787237", "cpu_usage": 0.2, "cpu_usage_per_core": [0.0, 0.0, 0.0, 0.0, 0.0, 0.0, 0.0, 0.0, 0.0, 0.0, 1.0, 0.0], "memory_usage": 5.9, "disk_usage": 3.6, "cpu_temp": 41.2, "gpu_temp": 40.0, "gpu_usage": [{"index": 0, "name": "NVIDIA GeForce GTX 1650 Ti", "usage": 0}], "nvme_temp": 30.9, "uptime": 1740172247.0}, {"timestamp": "2025-02-25T12:48:18.026661", "cpu_usage": 0.3, "cpu_usage_per_core": [0.0, 0.0, 1.0, 0.0, 0.0, 0.0, 0.0, 0.0, 0.0, 1.0, 1.0, 0.0], "memory_usage": 5.8, "disk_usage": 3.6, "cpu_temp": 41.2, "gpu_temp": 40.0, "gpu_usage": [{"index": 0, "name": "NVIDIA GeForce GTX 1650 Ti", "usage": 0}], "nvme_temp": 30.9, "uptime": 1740172247.0}, {"timestamp": "2025-02-25T12:48:21.340981", "cpu_usage": 0.2, "cpu_usage_per_core": [0.0, 0.0, 1.0, 0.0, 0.0, 0.0, 0.0, 0.0, 0.0, 0.0, 1.0, 0.0], "memory_usage": 5.8, "disk_usage": 3.6, "cpu_temp": 41.2, "gpu_temp": 39.0, "gpu_usage": [{"index": 0, "name": "NVIDIA GeForce GTX 1650 Ti", "usage": 0}], "nvme_temp": 30.9, "uptime": 1740172247.0}, {"timestamp": "2025-02-25T12:48:24.593787", "cpu_usage": 0.3, "cpu_usage_per_core": [0.0, 0.0, 0.0, 0.0, 0.0, 0.0, 2.0, 0.0, 0.0, 1.0, 0.0, 0.0], "memory_usage": 5.8, "disk_usage": 3.6, "cpu_temp": 41.1, "gpu_temp": 40.0, "gpu_usage": [{"index": 0, "name": "NVIDIA GeForce GTX 1650 Ti", "usage": 0}], "nvme_temp": 30.9, "uptime": 1740172247.0}, {"timestamp": "2025-02-25T12:48:27.899845", "cpu_usage": 0.4, "cpu_usage_per_core": [0.0, 0.0, 1.0, 1.0, 0.0, 0.0, 0.0, 0.0, 0.0, 2.0, 0.0, 0.0], "memory_usage": 5.8, "disk_usage": 3.6, "cpu_temp": 41.1, "gpu_temp": 39.0, "gpu_usage": [{"index": 0, "name": "NVIDIA GeForce GTX 1650 Ti", "usage": 0}], "nvme_temp": 30.9, "uptime": 1740172247.0}, {"timestamp": "2025-02-25T12:48:31.214336", "cpu_usage": 0.3, "cpu_usage_per_core": [0.0, 0.0, 0.0, 0.0, 0.0, 0.0, 0.0, 0.0, 0.0, 1.0, 1.0, 0.0], "memory_usage": 5.8, "disk_usage": 3.6, "cpu_temp": 41.1, "gpu_temp": 40.0, "gpu_usage": [{"index": 0, "name": "NVIDIA GeForce GTX 1650 Ti", "usage": 0}], "nvme_temp": 30.9, "uptime": 1740172247.0}, {"timestamp": "2025-02-25T12:48:34.506644", "cpu_usage": 0.3, "cpu_usage_per_core": [1.0, 0.0, 0.0, 0.0, 0.0, 0.0, 2.0, 0.0, 0.0, 1.0, 0.0, 0.0], "memory_usage": 5.8, "disk_usage": 3.6, "cpu_temp": 41.1, "gpu_temp": 39.0, "gpu_usage": [{"index": 0, "name": "NVIDIA GeForce GTX 1650 Ti", "usage": 0}], "nvme_temp": 30.9, "uptime": 1740172247.0}, {"timestamp": "2025-02-25T12:48:37.824725", "cpu_usage": 0.3, "cpu_usage_per_core": [2.1, 0.0, 0.0, 0.0, 0.0, 0.0, 0.0, 0.0, 0.0, 0.0, 1.0, 0.0], "memory_usage": 5.8, "disk_usage": 3.6, "cpu_temp": 41.1, "gpu_temp": 40.0, "gpu_usage": [{"index": 0, "name": "NVIDIA GeForce GTX 1650 Ti", "usage": 0}], "nvme_temp": 30.9, "uptime": 1740172247.0}, {"timestamp": "2025-02-25T12:48:41.145703", "cpu_usage": 0.2, "cpu_usage_per_core": [0.0, 1.0, 0.0, 0.0, 0.0, 0.0, 1.0, 0.0, 0.0, 1.0, 0.0, 0.0], "memory_usage": 5.9, "disk_usage": 3.6, "cpu_temp": 41.1, "gpu_temp": 39.0, "gpu_usage": [{"index": 0, "name": "NVIDIA GeForce GTX 1650 Ti", "usage": 0}], "nvme_temp": 30.9, "uptime": 1740172247.0}, {"timestamp": "2025-02-25T12:48:44.467639", "cpu_usage": 0.3, "cpu_usage_per_core": [0.0, 0.0, 1.0, 0.0, 0.0, 0.0, 1.0, 0.0, 0.0, 0.0, 0.0, 0.0], "memory_usage": 5.9, "disk_usage": 3.6, "cpu_temp": 41.0, "gpu_temp": 40.0, "gpu_usage": [{"index": 0, "name": "NVIDIA GeForce GTX 1650 Ti", "usage": 0}], "nvme_temp": 30.9, "uptime": 1740172247.0}, {"timestamp": "2025-02-25T12:48:47.774971", "cpu_usage": 0.3, "cpu_usage_per_core": [1.0, 0.0, 0.0, 0.0, 0.0, 0.0, 1.0, 0.0, 0.0, 1.0, 0.0, 0.0], "memory_usage": 5.9, "disk_usage": 3.6, "cpu_temp": 41.0, "gpu_temp": 39.0, "gpu_usage": [{"index": 0, "name": "NVIDIA GeForce GTX 1650 Ti", "usage": 0}], "nvme_temp": 30.9, "uptime": 1740172247.0}, {"timestamp": "2025-02-25T12:48:51.090941", "cpu_usage": 0.3, "cpu_usage_per_core": [1.0, 0.0, 0.0, 1.0, 0.0, 0.0, 0.0, 0.0, 0.0, 2.0, 0.0, 0.0], "memory_usage": 5.8, "disk_usage": 3.6, "cpu_temp": 41.0, "gpu_temp": 39.0, "gpu_usage": [{"index": 0, "name": "NVIDIA GeForce GTX 1650 Ti", "usage": 0}], "nvme_temp": 30.9, "uptime": 1740172247.0}, {"timestamp": "2025-02-25T12:48:54.433245", "cpu_usage": 0.1, "cpu_usage_per_core": [0.0, 0.0, 1.0, 0.0, 0.0, 0.0, 1.0, 0.0, 0.0, 0.0, 0.0, 0.0], "memory_usage": 5.8, "disk_usage": 3.6, "cpu_temp": 41.0, "gpu_temp": 39.0, "gpu_usage": [{"index": 0, "name": "NVIDIA GeForce GTX 1650 Ti", "usage": 0}], "nvme_temp": 30.9, "uptime": 1740172247.0}, {"timestamp": "2025-02-25T12:48:57.770426", "cpu_usage": 0.2, "cpu_usage_per_core": [1.0, 0.0, 0.0, 0.0, 0.0, 0.0, 0.0, 0.0, 0.0, 2.0, 1.0, 0.0], "memory_usage": 5.9, "disk_usage": 3.6, "cpu_temp": 41.0, "gpu_temp": 39.0, "gpu_usage": [{"index": 0, "name": "NVIDIA GeForce GTX 1650 Ti", "usage": 0}], "nvme_temp": 30.9, "uptime": 1740172247.0}, {"timestamp": "2025-02-25T12:49:01.088217", "cpu_usage": 0.8, "cpu_usage_per_core": [2.0, 0.0, 0.0, 0.0, 0.0, 0.0, 1.0, 0.0, 0.0, 1.0, 0.0, 0.0], "memory_usage": 5.8, "disk_usage": 3.6, "cpu_temp": 41.0, "gpu_temp": 39.0, "gpu_usage": [{"index": 0, "name": "NVIDIA GeForce GTX 1650 Ti", "usage": 0}], "nvme_temp": 30.9, "uptime": 1740172247.0}], "historical": [[{"timestamp": "2025-02-25T12:48:01.644276", "cpu_usage": 0.3, "cpu_usage_per_core": [1.0, 0.0, 0.0, 1.0, 1.0, 0.0, 1.0, 0.0, 0.0, 1.0, 4.9, 0.0], "memory_usage": 5.9, "disk_usage": 3.6, "cpu_temp": 41.2, "gpu_temp": 40.0, "gpu_usage": [{"index": 0, "name": "NVIDIA GeForce GTX 1650 Ti", "usage": 0}], "nvme_temp": 34.9, "uptime": 1740172247.0}, {"timestamp": "2025-02-25T12:48:04.898207", "cpu_usage": 0.3, "cpu_usage_per_core": [0.0, 0.0, 0.0, 0.0, 1.0, 0.0, 1.0, 0.0, 1.0, 0.0, 0.0, 0.0], "memory_usage": 5.8, "disk_usage": 3.6, "cpu_temp": 41.2, "gpu_temp": 40.0, "gpu_usage": [{"index": 0, "name": "NVIDIA GeForce GTX 1650 Ti", "usage": 0}], "nvme_temp": 31.9, "uptime": 1740172247.0}, {"timestamp": "2025-02-25T12:48:08.174531", "cpu_usage": 0.3, "cpu_usage_per_core": [1.0, 0.0, 0.0, 0.0, 0.0, 0.0, 0.0, 0.0, 0.0, 1.0, 2.0, 0.0], "memory_usage": 5.8, "disk_usage": 3.6, "cpu_temp": 41.2, "gpu_temp": 39.0, "gpu_usage": [{"index": 0, "name": "NVIDIA GeForce GTX 1650 Ti", "usage": 0}], "nvme_temp": 30.9, "uptime": 1740172247.0}, {"timestamp": "2025-02-25T12:48:11.468512", "cpu_usage": 0.3, "cpu_usage_per_core": [2.0, 0.0, 0.0, 0.0, 0.0, 0.0, 0.0, 0.0, 0.0, 0.0, 0.0, 0.0], "memory_usage": 5.9, "disk_usage": 3.6, "cpu_temp": 41.2, "gpu_temp": 40.0, "gpu_usage": [{"index": 0, "name": "NVIDIA GeForce GTX 1650 Ti", "usage": 0}], "nvme_temp": 30.9, "uptime": 1740172247.0}, {"timestamp": "2025-02-25T12:48:14.787237", "cpu_usage": 0.2, "cpu_usage_per_core": [0.0, 0.0, 0.0, 0.0, 0.0, 0.0, 0.0, 0.0, 0.0, 0.0, 1.0, 0.0], "memory_usage": 5.9, "disk_usage": 3.6, "cpu_temp": 41.2, "gpu_temp": 40.0, "gpu_usage": [{"index": 0, "name": "NVIDIA GeForce GTX 1650 Ti", "usage": 0}], "nvme_temp": 30.9, "uptime": 1740172247.0}, {"timestamp": "2025-02-25T12:48:18.026661", "cpu_usage": 0.3, "cpu_usage_per_core": [0.0, 0.0, 1.0, 0.0, 0.0, 0.0, 0.0, 0.0, 0.0, 1.0, 1.0, 0.0], "memory_usage": 5.8, "disk_usage": 3.6, "cpu_temp": 41.2, "gpu_temp": 40.0, "gpu_usage": [{"index": 0, "name": "NVIDIA GeForce GTX 1650 Ti", "usage": 0}], "nvme_temp": 30.9, "uptime": 1740172247.0}, {"timestamp": "2025-02-25T12:48:21.340981", "cpu_usage": 0.2, "cpu_usage_per_core": [0.0, 0.0, 1.0, 0.0, 0.0, 0.0, 0.0, 0.0, 0.0, 0.0, 1.0, 0.0], "memory_usage": 5.8, "disk_usage": 3.6, "cpu_temp": 41.2, "gpu_temp": 39.0, "gpu_usage": [{"index": 0, "name": "NVIDIA GeForce GTX 1650 Ti", "usage": 0}], "nvme_temp": 30.9, "uptime": 1740172247.0}, {"timestamp": "2025-02-25T12:48:24.593787", "cpu_usage": 0.3, "cpu_usage_per_core": [0.0, 0.0, 0.0, 0.0, 0.0, 0.0, 2.0, 0.0, 0.0, 1.0, 0.0, 0.0], "memory_usage": 5.8, "disk_usage": 3.6, "cpu_temp": 41.1, "gpu_temp": 40.0, "gpu_usage": [{"index": 0, "name": "NVIDIA GeForce GTX 1650 Ti", "usage": 0}], "nvme_temp": 30.9, "uptime": 1740172247.0}, {"timestamp": "2025-02-25T12:48:27.899845", "cpu_usage": 0.4, "cpu_usage_per_core": [0.0, 0.0, 1.0, 1.0, 0.0, 0.0, 0.0, 0.0, 0.0, 2.0, 0.0, 0.0], "memory_usage": 5.8, "disk_usage": 3.6, "cpu_temp": 41.1, "gpu_temp": 39.0, "gpu_usage": [{"index": 0, "name": "NVIDIA GeForce GTX 1650 Ti", "usage": 0}], "nvme_temp": 30.9, "uptime": 1740172247.0}, {"timestamp": "2025-02-25T12:48:31.214336", "cpu_usage": 0.3, "cpu_usage_per_core": [0.0, 0.0, 0.0, 0.0, 0.0, 0.0, 0.0, 0.0, 0.0, 1.0, 1.0, 0.0], "memory_usage": 5.8, "disk_usage": 3.6, "cpu_temp": 41.1, "gpu_temp": 40.0, "gpu_usage": [{"index": 0, "name": "NVIDIA GeForce GTX 1650 Ti", "usage": 0}], "nvme_temp": 30.9, "uptime": 1740172247.0}, {"timestamp": "2025-02-25T12:48:34.506644", "cpu_usage": 0.3, "cpu_usage_per_core": [1.0, 0.0, 0.0, 0.0, 0.0, 0.0, 2.0, 0.0, 0.0, 1.0, 0.0, 0.0], "memory_usage": 5.8, "disk_usage": 3.6, "cpu_temp": 41.1, "gpu_temp": 39.0, "gpu_usage": [{"index": 0, "name": "NVIDIA GeForce GTX 1650 Ti", "usage": 0}], "nvme_temp": 30.9, "uptime": 1740172247.0}, {"timestamp": "2025-02-25T12:48:37.824725", "cpu_usage": 0.3, "cpu_usage_per_core": [2.1, 0.0, 0.0, 0.0, 0.0, 0.0, 0.0, 0.0, 0.0, 0.0, 1.0, 0.0], "memory_usage": 5.8, "disk_usage": 3.6, "cpu_temp": 41.1, "gpu_temp": 40.0, "gpu_usage": [{"index": 0, "name": "NVIDIA GeForce GTX 1650 Ti", "usage": 0}], "nvme_temp": 30.9, "uptime": 1740172247.0}, {"timestamp": "2025-02-25T12:48:41.145703", "cpu_usage": 0.2, "cpu_usage_per_core": [0.0, 1.0, 0.0, 0.0, 0.0, 0.0, 1.0, 0.0, 0.0, 1.0, 0.0, 0.0], "memory_usage": 5.9, "disk_usage": 3.6, "cpu_temp": 41.1, "gpu_temp": 39.0, "gpu_usage": [{"index": 0, "name": "NVIDIA GeForce GTX 1650 Ti", "usage": 0}], "nvme_temp": 30.9, "uptime": 1740172247.0}, {"timestamp": "2025-02-25T12:48:44.467639", "cpu_usage": 0.3, "cpu_usage_per_core": [0.0, 0.0, 1.0, 0.0, 0.0, 0.0, 1.0, 0.0, 0.0, 0.0, 0.0, 0.0], "memory_usage": 5.9, "disk_usage": 3.6, "cpu_temp": 41.0, "gpu_temp": 40.0, "gpu_usage": [{"index": 0, "name": "NVIDIA GeForce GTX 1650 Ti", "usage": 0}], "nvme_temp": 30.9, "uptime": 1740172247.0}, {"timestamp": "2025-02-25T12:48:47.774971", "cpu_usage": 0.3, "cpu_usage_per_core": [1.0, 0.0, 0.0, 0.0, 0.0, 0.0, 1.0, 0.0, 0.0, 1.0, 0.0, 0.0], "memory_usage": 5.9, "disk_usage": 3.6, "cpu_temp": 41.0, "gpu_temp": 39.0, "gpu_usage": [{"index": 0, "name": "NVIDIA GeForce GTX 1650 Ti", "usage": 0}], "nvme_temp": 30.9, "uptime": 1740172247.0}, {"timestamp": "2025-02-25T12:48:51.090941", "cpu_usage": 0.3, "cpu_usage_per_core": [1.0, 0.0, 0.0, 1.0, 0.0, 0.0, 0.0, 0.0, 0.0, 2.0, 0.0, 0.0], "memory_usage": 5.8, "disk_usage": 3.6, "cpu_temp": 41.0, "gpu_temp": 39.0, "gpu_usage": [{"index": 0, "name": "NVIDIA GeForce GTX 1650 Ti", "usage": 0}], "nvme_temp": 30.9, "uptime": 1740172247.0}, {"timestamp": "2025-02-25T12:48:54.433245", "cpu_usage": 0.1, "cpu_usage_per_core": [0.0, 0.0, 1.0, 0.0, 0.0, 0.0, 1.0, 0.0, 0.0, 0.0, 0.0, 0.0], "memory_usage": 5.8, "disk_usage": 3.6, "cpu_temp": 41.0, "gpu_temp": 39.0, "gpu_usage": [{"index": 0, "name": "NVIDIA GeForce GTX 1650 Ti", "usage": 0}], "nvme_temp": 30.9, "uptime": 1740172247.0}, {"timestamp": "2025-02-25T12:48:57.770426", "cpu_usage": 0.2, "cpu_usage_per_core": [1.0, 0.0, 0.0, 0.0, 0.0, 0.0, 0.0, 0.0, 0.0, 2.0, 1.0, 0.0], "memory_usage": 5.9, "disk_usage": 3.6, "cpu_temp": 41.0, "gpu_temp": 39.0, "gpu_usage": [{"index": 0, "name": "NVIDIA GeForce GTX 1650 Ti", "usage": 0}], "nvme_temp": 30.9, "uptime": 1740172247.0}, {"timestamp": "2025-02-25T12:49:01.088217", "cpu_usage": 0.8, "cpu_usage_per_core": [2.0, 0.0, 0.0, 0.0, 0.0, 0.0, 1.0, 0.0, 0.0, 1.0, 0.0, 0.0], "memory_usage": 5.8, "disk_usage": 3.6, "cpu_temp": 41.0, "gpu_temp": 39.0, "gpu_usage": [{"index": 0, "name": "NVIDIA GeForce GTX 1650 Ti", "usage": 0}], "nvme_temp": 30.9, "uptime": 1740172247.0}]]}