{
    "current": [
        {
            "timestamp": "2025-02-25T21:46:01.677150+01:00",
            "cpu_usage": 0.4,
            "cpu_usage_per_core": [
                0.0,
                0.0,
                2.0,
                1.0,
                2.0,
                0.0,
                0.0,
                1.0,
                0.0,
                1.0,
                0.0,
                0.0
            ],
            "memory_usage": 8.2,
            "disk_usage": 3.7,
            "cpu_temp": 47.9,
            "gpu_temp": 40.0,
            "gpu_usage": [
                {
                    "index": 0,
                    "name": "NVIDIA GeForce GTX 1650 Ti",
                    "usage": 0
                }
            ],
            "nvme_temp": 33.9,
            "uptime": 1740172247.0
        },
        {
            "timestamp": "2025-02-25T21:46:04.913971+01:00",
            "cpu_usage": 1.0,
            "cpu_usage_per_core": [
                12.1,
                0.0,
                2.0,
                0.0,
                0.0,
                1.0,
                1.0,
                2.0,
                5.1,
                1.0,
                0.0,
                0.0
            ],
            "memory_usage": 8.1,
            "disk_usage": 3.7,
            "cpu_temp": 52.6,
            "gpu_temp": 40.0,
            "gpu_usage": [
                {
                    "index": 0,
                    "name": "NVIDIA GeForce GTX 1650 Ti",
                    "usage": 0
                }
            ],
            "nvme_temp": 32.9,
            "uptime": 1740172247.0
        },
        {
            "timestamp": "2025-02-25T21:46:08.164734+01:00",
            "cpu_usage": 0.3,
            "cpu_usage_per_core": [
                0.0,
                0.0,
                0.0,
                1.0,
                0.0,
                1.0,
                0.0,
                0.0,
                0.0,
                0.0,
                0.0,
                0.0
            ],
            "memory_usage": 8.2,
            "disk_usage": 3.7,
            "cpu_temp": 47.5,
            "gpu_temp": 40.0,
            "gpu_usage": [
                {
                    "index": 0,
                    "name": "NVIDIA GeForce GTX 1650 Ti",
                    "usage": 0
                }
            ],
            "nvme_temp": 31.9,
            "uptime": 1740172247.0
        },
        {
            "timestamp": "2025-02-25T21:46:11.478811+01:00",
            "cpu_usage": 0.2,
            "cpu_usage_per_core": [
                1.0,
                0.0,
                0.0,
                0.0,
                0.0,
                0.0,
                0.0,
                0.0,
                0.0,
                0.0,
                0.0,
                0.0
            ],
            "memory_usage": 8.1,
            "disk_usage": 3.7,
            "cpu_temp": 42.4,
            "gpu_temp": 40.0,
            "gpu_usage": [
                {
                    "index": 0,
                    "name": "NVIDIA GeForce GTX 1650 Ti",
                    "usage": 0
                }
            ],
            "nvme_temp": 32.9,
            "uptime": 1740172247.0
        },
        {
            "timestamp": "2025-02-25T21:46:14.803586+01:00",
            "cpu_usage": 0.5,
            "cpu_usage_per_core": [
                1.0,
                1.0,
                1.0,
                0.0,
                4.1,
                0.0,
                1.0,
                7.9,
                3.0,
                1.0,
                0.0,
                0.0
            ],
            "memory_usage": 8.1,
            "disk_usage": 3.7,
            "cpu_temp": 49.4,
            "gpu_temp": 40.0,
            "gpu_usage": [
                {
                    "index": 0,
                    "name": "NVIDIA GeForce GTX 1650 Ti",
                    "usage": 0
                }
            ],
            "nvme_temp": 31.9,
            "uptime": 1740172247.0
        },
        {
            "timestamp": "2025-02-25T21:46:18.127539+01:00",
            "cpu_usage": 0.3,
            "cpu_usage_per_core": [
                1.0,
                0.0,
                0.0,
                0.0,
                0.0,
                0.0,
                0.0,
                0.0,
                0.0,
                0.0,
                0.0,
                0.0
            ],
            "memory_usage": 8.1,
            "disk_usage": 3.7,
            "cpu_temp": 44.1,
            "gpu_temp": 40.0,
            "gpu_usage": [
                {
                    "index": 0,
                    "name": "NVIDIA GeForce GTX 1650 Ti",
                    "usage": 0
                }
            ],
            "nvme_temp": 31.9,
            "uptime": 1740172247.0
        },
        {
            "timestamp": "2025-02-25T21:46:21.435134+01:00",
            "cpu_usage": 0.3,
            "cpu_usage_per_core": [
                0.0,
                0.0,
                0.0,
                0.0,
                0.0,
                0.0,
                1.0,
                0.0,
                0.0,
                0.0,
                0.0,
                0.0
            ],
            "memory_usage": 8.1,
            "disk_usage": 3.7,
            "cpu_temp": 41.8,
            "gpu_temp": 40.0,
            "gpu_usage": [
                {
                    "index": 0,
                    "name": "NVIDIA GeForce GTX 1650 Ti",
                    "usage": 0
                }
            ],
            "nvme_temp": 31.9,
            "uptime": 1740172247.0
        },
        {
            "timestamp": "2025-02-25T21:46:24.793644+01:00",
            "cpu_usage": 0.1,
            "cpu_usage_per_core": [
                0.0,
                0.0,
                0.0,
                1.0,
                0.0,
                0.0,
                0.0,
                0.0,
                0.0,
                1.0,
                0.0,
                0.0
            ],
            "memory_usage": 8.1,
            "disk_usage": 3.7,
            "cpu_temp": 41.5,
            "gpu_temp": 40.0,
            "gpu_usage": [
                {
                    "index": 0,
                    "name": "NVIDIA GeForce GTX 1650 Ti",
                    "usage": 0
                }
            ],
            "nvme_temp": 30.9,
            "uptime": 1740172247.0
        },
        {
            "timestamp": "2025-02-25T21:46:28.098519+01:00",
            "cpu_usage": 0.2,
            "cpu_usage_per_core": [
                1.0,
                0.0,
                1.0,
                0.0,
                0.0,
                0.0,
                1.0,
                0.0,
                0.0,
                0.0,
                0.0,
                0.0
            ],
            "memory_usage": 8.2,
            "disk_usage": 3.7,
            "cpu_temp": 41.5,
            "gpu_temp": 39.0,
            "gpu_usage": [
                {
                    "index": 0,
                    "name": "NVIDIA GeForce GTX 1650 Ti",
                    "usage": 0
                }
            ],
            "nvme_temp": 30.9,
            "uptime": 1740172247.0
        },
        {
            "timestamp": "2025-02-25T21:46:31.459774+01:00",
            "cpu_usage": 0.2,
            "cpu_usage_per_core": [
                0.0,
                0.0,
                1.0,
                0.0,
                0.0,
                0.0,
                0.0,
                0.0,
                1.0,
                0.0,
                0.0,
                0.0
            ],
            "memory_usage": 8.1,
            "disk_usage": 3.7,
            "cpu_temp": 41.5,
            "gpu_temp": 40.0,
            "gpu_usage": [
                {
                    "index": 0,
                    "name": "NVIDIA GeForce GTX 1650 Ti",
                    "usage": 0
                }
            ],
            "nvme_temp": 31.9,
            "uptime": 1740172247.0
        },
        {
            "timestamp": "2025-02-25T21:46:34.849075+01:00",
            "cpu_usage": 0.1,
            "cpu_usage_per_core": [
                1.0,
                0.0,
                1.0,
                0.0,
                0.0,
                0.0,
                1.0,
                0.0,
                0.0,
                0.0,
                0.0,
                0.0
            ],
            "memory_usage": 8.1,
            "disk_usage": 3.7,
            "cpu_temp": 41.2,
            "gpu_temp": 40.0,
            "gpu_usage": [
                {
                    "index": 0,
                    "name": "NVIDIA GeForce GTX 1650 Ti",
                    "usage": 0
                }
            ],
            "nvme_temp": 31.9,
            "uptime": 1740172247.0
        },
        {
            "timestamp": "2025-02-25T21:46:38.189763+01:00",
            "cpu_usage": 0.1,
            "cpu_usage_per_core": [
                0.0,
                0.0,
                1.0,
                0.0,
                0.0,
                0.0,
                0.0,
                0.0,
                0.0,
                0.0,
                0.0,
                0.0
            ],
            "memory_usage": 8.1,
            "disk_usage": 3.7,
            "cpu_temp": 41.2,
            "gpu_temp": 40.0,
            "gpu_usage": [
                {
                    "index": 0,
                    "name": "NVIDIA GeForce GTX 1650 Ti",
                    "usage": 0
                }
            ],
            "nvme_temp": 31.9,
            "uptime": 1740172247.0
        },
        {
            "timestamp": "2025-02-25T21:46:41.526391+01:00",
            "cpu_usage": 0.1,
            "cpu_usage_per_core": [
                0.0,
                0.0,
                1.0,
                0.0,
                0.0,
                0.0,
                0.0,
                0.0,
                0.0,
                0.0,
                0.0,
                0.0
            ],
            "memory_usage": 8.1,
            "disk_usage": 3.7,
            "cpu_temp": 41.2,
            "gpu_temp": 40.0,
            "gpu_usage": [
                {
                    "index": 0,
                    "name": "NVIDIA GeForce GTX 1650 Ti",
                    "usage": 0
                }
            ],
            "nvme_temp": 31.9,
            "uptime": 1740172247.0
        },
        {
            "timestamp": "2025-02-25T21:46:44.875292+01:00",
            "cpu_usage": 0.1,
            "cpu_usage_per_core": [
                0.0,
                0.0,
                1.0,
                0.0,
                1.0,
                0.0,
                0.0,
                0.0,
                0.0,
                0.0,
                0.0,
                0.0
            ],
            "memory_usage": 8.1,
            "disk_usage": 3.7,
            "cpu_temp": 41.1,
            "gpu_temp": 39.0,
            "gpu_usage": [
                {
                    "index": 0,
                    "name": "NVIDIA GeForce GTX 1650 Ti",
                    "usage": 0
                }
            ],
            "nvme_temp": 31.9,
            "uptime": 1740172247.0
        },
        {
            "timestamp": "2025-02-25T21:46:48.215499+01:00",
            "cpu_usage": 0.2,
            "cpu_usage_per_core": [
                0.0,
                1.0,
                0.0,
                0.0,
                0.0,
                0.0,
                0.0,
                1.0,
                0.0,
                0.0,
                0.0,
                0.0
            ],
            "memory_usage": 8.1,
            "disk_usage": 3.7,
            "cpu_temp": 41.1,
            "gpu_temp": 40.0,
            "gpu_usage": [
                {
                    "index": 0,
                    "name": "NVIDIA GeForce GTX 1650 Ti",
                    "usage": 0
                }
            ],
            "nvme_temp": 30.9,
            "uptime": 1740172247.0
        },
        {
            "timestamp": "2025-02-25T21:46:51.565346+01:00",
            "cpu_usage": 0.1,
            "cpu_usage_per_core": [
                0.0,
                0.0,
                1.0,
                0.0,
                0.0,
                0.0,
                0.0,
                0.0,
                0.0,
                0.0,
                0.0,
                0.0
            ],
            "memory_usage": 8.1,
            "disk_usage": 3.7,
            "cpu_temp": 41.1,
            "gpu_temp": 39.0,
            "gpu_usage": [
                {
                    "index": 0,
                    "name": "NVIDIA GeForce GTX 1650 Ti",
                    "usage": 0
                }
            ],
            "nvme_temp": 30.9,
            "uptime": 1740172247.0
        },
        {
            "timestamp": "2025-02-25T21:46:54.908238+01:00",
            "cpu_usage": 0.0,
            "cpu_usage_per_core": [
                0.0,
                0.0,
                1.0,
                0.0,
                0.0,
                0.0,
                0.0,
                0.0,
                0.0,
                0.0,
                0.0,
                0.0
            ],
            "memory_usage": 8.1,
            "disk_usage": 3.7,
            "cpu_temp": 41.1,
            "gpu_temp": 39.0,
            "gpu_usage": [
                {
                    "index": 0,
                    "name": "NVIDIA GeForce GTX 1650 Ti",
                    "usage": 0
                }
            ],
            "nvme_temp": 30.9,
            "uptime": 1740172247.0
        },
        {
            "timestamp": "2025-02-25T21:46:58.191236+01:00",
            "cpu_usage": 0.1,
            "cpu_usage_per_core": [
                0.0,
                0.0,
                1.0,
                1.0,
                0.0,
                0.0,
                0.0,
                3.0,
                0.0,
                0.0,
                0.0,
                0.0
            ],
            "memory_usage": 8.1,
            "disk_usage": 3.7,
            "cpu_temp": 41.1,
            "gpu_temp": 39.0,
            "gpu_usage": [
                {
                    "index": 0,
                    "name": "NVIDIA GeForce GTX 1650 Ti",
                    "usage": 0
                }
            ],
            "nvme_temp": 31.9,
            "uptime": 1740172247.0
        },
        {
            "timestamp": "2025-02-25T21:47:01.460830+01:00",
            "cpu_usage": 0.2,
            "cpu_usage_per_core": [
                0.0,
                0.0,
                0.0,
                0.0,
                1.0,
                1.0,
                0.0,
                0.0,
                0.0,
                0.0,
                0.0,
                0.0
            ],
            "memory_usage": 8.2,
            "disk_usage": 3.7,
            "cpu_temp": 41.1,
            "gpu_temp": 39.0,
            "gpu_usage": [
                {
                    "index": 0,
                    "name": "NVIDIA GeForce GTX 1650 Ti",
                    "usage": 0
                }
            ],
            "nvme_temp": 30.9,
            "uptime": 1740172247.0
        }
    ],
    "historical": [
        {
            "timestamp": "2025-02-25T21:46:01.677150+01:00",
            "cpu_usage": 0.4,
            "cpu_usage_per_core": [
                0.0,
                0.0,
                2.0,
                1.0,
                2.0,
                0.0,
                0.0,
                1.0,
                0.0,
                1.0,
                0.0,
                0.0
            ],
            "memory_usage": 8.2,
            "disk_usage": 3.7,
            "cpu_temp": 47.9,
            "gpu_temp": 40.0,
            "gpu_usage": [
                {
                    "index": 0,
                    "name": "NVIDIA GeForce GTX 1650 Ti",
                    "usage": 0
                }
            ],
            "nvme_temp": 33.9,
            "uptime": 1740172247.0
        },
        {
            "timestamp": "2025-02-25T21:46:04.913971+01:00",
            "cpu_usage": 1.0,
            "cpu_usage_per_core": [
                12.1,
                0.0,
                2.0,
                0.0,
                0.0,
                1.0,
                1.0,
                2.0,
                5.1,
                1.0,
                0.0,
                0.0
            ],
            "memory_usage": 8.1,
            "disk_usage": 3.7,
            "cpu_temp": 52.6,
            "gpu_temp": 40.0,
            "gpu_usage": [
                {
                    "index": 0,
                    "name": "NVIDIA GeForce GTX 1650 Ti",
                    "usage": 0
                }
            ],
            "nvme_temp": 32.9,
            "uptime": 1740172247.0
        },
        {
            "timestamp": "2025-02-25T21:46:08.164734+01:00",
            "cpu_usage": 0.3,
            "cpu_usage_per_core": [
                0.0,
                0.0,
                0.0,
                1.0,
                0.0,
                1.0,
                0.0,
                0.0,
                0.0,
                0.0,
                0.0,
                0.0
            ],
            "memory_usage": 8.2,
            "disk_usage": 3.7,
            "cpu_temp": 47.5,
            "gpu_temp": 40.0,
            "gpu_usage": [
                {
                    "index": 0,
                    "name": "NVIDIA GeForce GTX 1650 Ti",
                    "usage": 0
                }
            ],
            "nvme_temp": 31.9,
            "uptime": 1740172247.0
        },
        {
            "timestamp": "2025-02-25T21:46:11.478811+01:00",
            "cpu_usage": 0.2,
            "cpu_usage_per_core": [
                1.0,
                0.0,
                0.0,
                0.0,
                0.0,
                0.0,
                0.0,
                0.0,
                0.0,
                0.0,
                0.0,
                0.0
            ],
            "memory_usage": 8.1,
            "disk_usage": 3.7,
            "cpu_temp": 42.4,
            "gpu_temp": 40.0,
            "gpu_usage": [
                {
                    "index": 0,
                    "name": "NVIDIA GeForce GTX 1650 Ti",
                    "usage": 0
                }
            ],
            "nvme_temp": 32.9,
            "uptime": 1740172247.0
        },
        {
            "timestamp": "2025-02-25T21:46:14.803586+01:00",
            "cpu_usage": 0.5,
            "cpu_usage_per_core": [
                1.0,
                1.0,
                1.0,
                0.0,
                4.1,
                0.0,
                1.0,
                7.9,
                3.0,
                1.0,
                0.0,
                0.0
            ],
            "memory_usage": 8.1,
            "disk_usage": 3.7,
            "cpu_temp": 49.4,
            "gpu_temp": 40.0,
            "gpu_usage": [
                {
                    "index": 0,
                    "name": "NVIDIA GeForce GTX 1650 Ti",
                    "usage": 0
                }
            ],
            "nvme_temp": 31.9,
            "uptime": 1740172247.0
        },
        {
            "timestamp": "2025-02-25T21:46:18.127539+01:00",
            "cpu_usage": 0.3,
            "cpu_usage_per_core": [
                1.0,
                0.0,
                0.0,
                0.0,
                0.0,
                0.0,
                0.0,
                0.0,
                0.0,
                0.0,
                0.0,
                0.0
            ],
            "memory_usage": 8.1,
            "disk_usage": 3.7,
            "cpu_temp": 44.1,
            "gpu_temp": 40.0,
            "gpu_usage": [
                {
                    "index": 0,
                    "name": "NVIDIA GeForce GTX 1650 Ti",
                    "usage": 0
                }
            ],
            "nvme_temp": 31.9,
            "uptime": 1740172247.0
        },
        {
            "timestamp": "2025-02-25T21:46:21.435134+01:00",
            "cpu_usage": 0.3,
            "cpu_usage_per_core": [
                0.0,
                0.0,
                0.0,
                0.0,
                0.0,
                0.0,
                1.0,
                0.0,
                0.0,
                0.0,
                0.0,
                0.0
            ],
            "memory_usage": 8.1,
            "disk_usage": 3.7,
            "cpu_temp": 41.8,
            "gpu_temp": 40.0,
            "gpu_usage": [
                {
                    "index": 0,
                    "name": "NVIDIA GeForce GTX 1650 Ti",
                    "usage": 0
                }
            ],
            "nvme_temp": 31.9,
            "uptime": 1740172247.0
        },
        {
            "timestamp": "2025-02-25T21:46:24.793644+01:00",
            "cpu_usage": 0.1,
            "cpu_usage_per_core": [
                0.0,
                0.0,
                0.0,
                1.0,
                0.0,
                0.0,
                0.0,
                0.0,
                0.0,
                1.0,
                0.0,
                0.0
            ],
            "memory_usage": 8.1,
            "disk_usage": 3.7,
            "cpu_temp": 41.5,
            "gpu_temp": 40.0,
            "gpu_usage": [
                {
                    "index": 0,
                    "name": "NVIDIA GeForce GTX 1650 Ti",
                    "usage": 0
                }
            ],
            "nvme_temp": 30.9,
            "uptime": 1740172247.0
        },
        {
            "timestamp": "2025-02-25T21:46:28.098519+01:00",
            "cpu_usage": 0.2,
            "cpu_usage_per_core": [
                1.0,
                0.0,
                1.0,
                0.0,
                0.0,
                0.0,
                1.0,
                0.0,
                0.0,
                0.0,
                0.0,
                0.0
            ],
            "memory_usage": 8.2,
            "disk_usage": 3.7,
            "cpu_temp": 41.5,
            "gpu_temp": 39.0,
            "gpu_usage": [
                {
                    "index": 0,
                    "name": "NVIDIA GeForce GTX 1650 Ti",
                    "usage": 0
                }
            ],
            "nvme_temp": 30.9,
            "uptime": 1740172247.0
        },
        {
            "timestamp": "2025-02-25T21:46:31.459774+01:00",
            "cpu_usage": 0.2,
            "cpu_usage_per_core": [
                0.0,
                0.0,
                1.0,
                0.0,
                0.0,
                0.0,
                0.0,
                0.0,
                1.0,
                0.0,
                0.0,
                0.0
            ],
            "memory_usage": 8.1,
            "disk_usage": 3.7,
            "cpu_temp": 41.5,
            "gpu_temp": 40.0,
            "gpu_usage": [
                {
                    "index": 0,
                    "name": "NVIDIA GeForce GTX 1650 Ti",
                    "usage": 0
                }
            ],
            "nvme_temp": 31.9,
            "uptime": 1740172247.0
        },
        {
            "timestamp": "2025-02-25T21:46:34.849075+01:00",
            "cpu_usage": 0.1,
            "cpu_usage_per_core": [
                1.0,
                0.0,
                1.0,
                0.0,
                0.0,
                0.0,
                1.0,
                0.0,
                0.0,
                0.0,
                0.0,
                0.0
            ],
            "memory_usage": 8.1,
            "disk_usage": 3.7,
            "cpu_temp": 41.2,
            "gpu_temp": 40.0,
            "gpu_usage": [
                {
                    "index": 0,
                    "name": "NVIDIA GeForce GTX 1650 Ti",
                    "usage": 0
                }
            ],
            "nvme_temp": 31.9,
            "uptime": 1740172247.0
        },
        {
            "timestamp": "2025-02-25T21:46:38.189763+01:00",
            "cpu_usage": 0.1,
            "cpu_usage_per_core": [
                0.0,
                0.0,
                1.0,
                0.0,
                0.0,
                0.0,
                0.0,
                0.0,
                0.0,
                0.0,
                0.0,
                0.0
            ],
            "memory_usage": 8.1,
            "disk_usage": 3.7,
            "cpu_temp": 41.2,
            "gpu_temp": 40.0,
            "gpu_usage": [
                {
                    "index": 0,
                    "name": "NVIDIA GeForce GTX 1650 Ti",
                    "usage": 0
                }
            ],
            "nvme_temp": 31.9,
            "uptime": 1740172247.0
        },
        {
            "timestamp": "2025-02-25T21:46:41.526391+01:00",
            "cpu_usage": 0.1,
            "cpu_usage_per_core": [
                0.0,
                0.0,
                1.0,
                0.0,
                0.0,
                0.0,
                0.0,
                0.0,
                0.0,
                0.0,
                0.0,
                0.0
            ],
            "memory_usage": 8.1,
            "disk_usage": 3.7,
            "cpu_temp": 41.2,
            "gpu_temp": 40.0,
            "gpu_usage": [
                {
                    "index": 0,
                    "name": "NVIDIA GeForce GTX 1650 Ti",
                    "usage": 0
                }
            ],
            "nvme_temp": 31.9,
            "uptime": 1740172247.0
        },
        {
            "timestamp": "2025-02-25T21:46:44.875292+01:00",
            "cpu_usage": 0.1,
            "cpu_usage_per_core": [
                0.0,
                0.0,
                1.0,
                0.0,
                1.0,
                0.0,
                0.0,
                0.0,
                0.0,
                0.0,
                0.0,
                0.0
            ],
            "memory_usage": 8.1,
            "disk_usage": 3.7,
            "cpu_temp": 41.1,
            "gpu_temp": 39.0,
            "gpu_usage": [
                {
                    "index": 0,
                    "name": "NVIDIA GeForce GTX 1650 Ti",
                    "usage": 0
                }
            ],
            "nvme_temp": 31.9,
            "uptime": 1740172247.0
        },
        {
            "timestamp": "2025-02-25T21:46:48.215499+01:00",
            "cpu_usage": 0.2,
            "cpu_usage_per_core": [
                0.0,
                1.0,
                0.0,
                0.0,
                0.0,
                0.0,
                0.0,
                1.0,
                0.0,
                0.0,
                0.0,
                0.0
            ],
            "memory_usage": 8.1,
            "disk_usage": 3.7,
            "cpu_temp": 41.1,
            "gpu_temp": 40.0,
            "gpu_usage": [
                {
                    "index": 0,
                    "name": "NVIDIA GeForce GTX 1650 Ti",
                    "usage": 0
                }
            ],
            "nvme_temp": 30.9,
            "uptime": 1740172247.0
        },
        {
            "timestamp": "2025-02-25T21:46:51.565346+01:00",
            "cpu_usage": 0.1,
            "cpu_usage_per_core": [
                0.0,
                0.0,
                1.0,
                0.0,
                0.0,
                0.0,
                0.0,
                0.0,
                0.0,
                0.0,
                0.0,
                0.0
            ],
            "memory_usage": 8.1,
            "disk_usage": 3.7,
            "cpu_temp": 41.1,
            "gpu_temp": 39.0,
            "gpu_usage": [
                {
                    "index": 0,
                    "name": "NVIDIA GeForce GTX 1650 Ti",
                    "usage": 0
                }
            ],
            "nvme_temp": 30.9,
            "uptime": 1740172247.0
        },
        {
            "timestamp": "2025-02-25T21:46:54.908238+01:00",
            "cpu_usage": 0.0,
            "cpu_usage_per_core": [
                0.0,
                0.0,
                1.0,
                0.0,
                0.0,
                0.0,
                0.0,
                0.0,
                0.0,
                0.0,
                0.0,
                0.0
            ],
            "memory_usage": 8.1,
            "disk_usage": 3.7,
            "cpu_temp": 41.1,
            "gpu_temp": 39.0,
            "gpu_usage": [
                {
                    "index": 0,
                    "name": "NVIDIA GeForce GTX 1650 Ti",
                    "usage": 0
                }
            ],
            "nvme_temp": 30.9,
            "uptime": 1740172247.0
        },
        {
            "timestamp": "2025-02-25T21:46:58.191236+01:00",
            "cpu_usage": 0.1,
            "cpu_usage_per_core": [
                0.0,
                0.0,
                1.0,
                1.0,
                0.0,
                0.0,
                0.0,
                3.0,
                0.0,
                0.0,
                0.0,
                0.0
            ],
            "memory_usage": 8.1,
            "disk_usage": 3.7,
            "cpu_temp": 41.1,
            "gpu_temp": 39.0,
            "gpu_usage": [
                {
                    "index": 0,
                    "name": "NVIDIA GeForce GTX 1650 Ti",
                    "usage": 0
                }
            ],
            "nvme_temp": 31.9,
            "uptime": 1740172247.0
        },
        {
            "timestamp": "2025-02-25T21:47:01.460830+01:00",
            "cpu_usage": 0.2,
            "cpu_usage_per_core": [
                0.0,
                0.0,
                0.0,
                0.0,
                1.0,
                1.0,
                0.0,
                0.0,
                0.0,
                0.0,
                0.0,
                0.0
            ],
            "memory_usage": 8.2,
            "disk_usage": 3.7,
            "cpu_temp": 41.1,
            "gpu_temp": 39.0,
            "gpu_usage": [
                {
                    "index": 0,
                    "name": "NVIDIA GeForce GTX 1650 Ti",
                    "usage": 0
                }
            ],
            "nvme_temp": 30.9,
            "uptime": 1740172247.0
        }
    ]
}